<?xml version="1.0" encoding="utf-8"?>
<Trade xmlns:xsi="http://www.w3.org/2001/XMLSchema-instance" xmlns:xsd="http://www.w3.org/2001/XMLSchema">
  <swap xmlns="http://www.fpml.org/FpML-5/reporting">
    <productType>Swap</productType>
    <swapStream>
      <payerPartyReference href="Party1" />
      <receiverPartyReference href="Party2" />
      <calculationPeriodDates>
        <effectiveDate>
          <unadjustedDate id="unadjustedDate">2013-05-27</unadjustedDate>
          <dateAdjustments>
            <businessDayConvention>NONE</businessDayConvention>
          </dateAdjustments>
        </effectiveDate>
        <terminationDate>
          <unadjustedDate id="unadjustedDate">2023-05-29</unadjustedDate>
          <dateAdjustments>
            <businessDayConvention>MODFOLLOWING</businessDayConvention>
            <businessCenters>
              <businessCenter>Sydney</businessCenter>
            </businessCenters>
          </dateAdjustments>
        </terminationDate>
        <calculationPeriodDatesAdjustments>
          <businessCenters>
            <businessCenter>Sydney</businessCenter>
          </businessCenters>
        </calculationPeriodDatesAdjustments>
        <firstPeriodStartDate id="FullFirstCoupon">
          <dateAdjustments>
            <businessCenters>
              <businessCenter>Sydney</businessCenter>
            </businessCenters>
          </dateAdjustments>
        </firstPeriodStartDate>
        <calculationPeriodFrequency>
          <periodMultiplier>6</periodMultiplier>
          <period>M</period>
        </calculationPeriodFrequency>
      </calculationPeriodDates>
      <paymentDates>
        <paymentFrequency>
          <periodMultiplier>6</periodMultiplier>
          <period>M</period>
        </paymentFrequency>
        <paymentDatesAdjustments>
          <businessCenters>
            <businessCenter>Sydney</businessCenter>
          </businessCenters>
        </paymentDatesAdjustments>
      </paymentDates>
      <calculationPeriodAmount>
        <calculation>
          <notionalSchedule>
            <notionalStepSchedule>
              <initialValue>100000000</initialValue>
              <currency>AUD</currency>
            </notionalStepSchedule>
          </notionalSchedule>
          <fixedRateSchedule>
            <initialValue>0.05</initialValue>
          </fixedRateSchedule>
          <dayCountFraction>ACT/365.FIXED</dayCountFraction>
        </calculation>
      </calculationPeriodAmount>
      <principalExchanges />
      <cashflows>
        <principalExchange>
          <adjustedPrincipalExchangeDate>2013-05-27</adjustedPrincipalExchangeDate>
          <principalExchangeAmount>-100000000</principalExchangeAmount>
          <discountFactor>0.999637939354568</discountFactor>
          <presentValuePrincipalExchangeAmount>
            <currency>CURRENCY NOT SPECIFIED</currency>
            <amount>-99963793.935456800000000</amount>
          </presentValuePrincipalExchangeAmount>
        </principalExchange>
        <principalExchange>
          <adjustedPrincipalExchangeDate>2023-05-29</adjustedPrincipalExchangeDate>
          <principalExchangeAmount>100000000</principalExchangeAmount>
          <discountFactor>0.509205226195311</discountFactor>
          <presentValuePrincipalExchangeAmount>
            <currency>CURRENCY NOT SPECIFIED</currency>
            <amount>50920522.619531100000000</amount>
          </presentValuePrincipalExchangeAmount>
        </principalExchange>
        <paymentCalculationPeriod>
          <adjustedPaymentDate>2013-11-29</adjustedPaymentDate>
          <calculationPeriod>
            <unadjustedStartDate>2013-05-27</unadjustedStartDate>
            <unadjustedEndDate>2013-11-29</unadjustedEndDate>
            <adjustedStartDate>2013-05-27</adjustedStartDate>
            <adjustedEndDate>2013-11-29</adjustedEndDate>
            <calculationPeriodNumberOfDays>186</calculationPeriodNumberOfDays>
            <notionalAmount>100000000</notionalAmount>
            <fixedRate>0.05</fixedRate>
            <dayCountYearFraction>0.50958904109589</dayCountYearFraction>
          </calculationPeriod>
          <discountFactor>0.966751410654946</discountFactor>
          <forecastPaymentAmount>
            <currency>AUD</currency>
            <amount>2547945.2054794500000000</amount>
          </forecastPaymentAmount>
          <presentValueAmount>
            <currency>AUD</currency>
            <amount>2463229.6216687645340724438597</amount>
          </presentValueAmount>
        </paymentCalculationPeriod>
        <paymentCalculationPeriod>
          <adjustedPaymentDate>2014-05-29</adjustedPaymentDate>
          <calculationPeriod>
            <unadjustedStartDate>2013-11-29</unadjustedStartDate>
            <unadjustedEndDate>2014-05-29</unadjustedEndDate>
            <adjustedStartDate>2013-11-29</adjustedStartDate>
            <adjustedEndDate>2014-05-29</adjustedEndDate>
            <calculationPeriodNumberOfDays>181</calculationPeriodNumberOfDays>
            <notionalAmount>100000000</notionalAmount>
            <fixedRate>0.05</fixedRate>
            <dayCountYearFraction>0.495890410958904</dayCountYearFraction>
          </calculationPeriod>
          <discountFactor>0.934993101284599</discountFactor>
          <forecastPaymentAmount>
            <currency>AUD</currency>
            <amount>2479452.05479452000000000</amount>
          </forecastPaymentAmount>
          <presentValueAmount>
            <currency>AUD</currency>
            <amount>2318270.5661987997479489855975</amount>
          </presentValueAmount>
        </paymentCalculationPeriod>
        <paymentCalculationPeriod>
          <adjustedPaymentDate>2014-11-28</adjustedPaymentDate>
          <calculationPeriod>
            <unadjustedStartDate>2014-05-29</unadjustedStartDate>
            <unadjustedEndDate>2014-11-29</unadjustedEndDate>
            <adjustedStartDate>2014-05-29</adjustedStartDate>
            <adjustedEndDate>2014-11-28</adjustedEndDate>
            <calculationPeriodNumberOfDays>183</calculationPeriodNumberOfDays>
            <notionalAmount>100000000</notionalAmount>
            <fixedRate>0.05</fixedRate>
            <dayCountYearFraction>0.501369863013699</dayCountYearFraction>
          </calculationPeriod>
          <discountFactor>0.905169804478298</discountFactor>
          <forecastPaymentAmount>
            <currency>AUD</currency>
            <amount>2506849.31506849500000000</amount>
          </forecastPaymentAmount>
          <presentValueAmount>
            <currency>AUD</currency>
            <amount>2269124.3043771048794236110215</amount>
          </presentValueAmount>
        </paymentCalculationPeriod>
        <paymentCalculationPeriod>
          <adjustedPaymentDate>2015-05-29</adjustedPaymentDate>
          <calculationPeriod>
            <unadjustedStartDate>2014-11-29</unadjustedStartDate>
            <unadjustedEndDate>2015-05-29</unadjustedEndDate>
            <adjustedStartDate>2014-11-28</adjustedStartDate>
            <adjustedEndDate>2015-05-29</adjustedEndDate>
            <calculationPeriodNumberOfDays>182</calculationPeriodNumberOfDays>
            <notionalAmount>100000000</notionalAmount>
            <fixedRate>0.05</fixedRate>
            <dayCountYearFraction>0.498630136986301</dayCountYearFraction>
          </calculationPeriod>
          <discountFactor>0.875610231343901</discountFactor>
          <forecastPaymentAmount>
            <currency>AUD</currency>
            <amount>2493150.68493150500000000</amount>
          </forecastPaymentAmount>
          <presentValueAmount>
            <currency>AUD</currency>
            <amount>2183028.2480080803259262845010</amount>
          </presentValueAmount>
        </paymentCalculationPeriod>
        <paymentCalculationPeriod>
          <adjustedPaymentDate>2015-11-30</adjustedPaymentDate>
          <calculationPeriod>
            <unadjustedStartDate>2015-05-29</unadjustedStartDate>
            <unadjustedEndDate>2015-11-29</unadjustedEndDate>
            <adjustedStartDate>2015-05-29</adjustedStartDate>
            <adjustedEndDate>2015-11-30</adjustedEndDate>
            <calculationPeriodNumberOfDays>185</calculationPeriodNumberOfDays>
            <notionalAmount>100000000</notionalAmount>
            <fixedRate>0.05</fixedRate>
            <dayCountYearFraction>0.506849315068493</dayCountYearFraction>
          </calculationPeriod>
          <discountFactor>0.838119826272326</discountFactor>
          <forecastPaymentAmount>
            <currency>AUD</currency>
            <amount>2534246.57534246500000000</amount>
          </forecastPaymentAmount>
          <presentValueAmount>
            <currency>AUD</currency>
            <amount>2124002.2994572638890878021236</amount>
          </presentValueAmount>
        </paymentCalculationPeriod>
        <paymentCalculationPeriod>
          <adjustedPaymentDate>2016-05-30</adjustedPaymentDate>
          <calculationPeriod>
            <unadjustedStartDate>2015-11-29</unadjustedStartDate>
            <unadjustedEndDate>2016-05-29</unadjustedEndDate>
            <adjustedStartDate>2015-11-30</adjustedStartDate>
            <adjustedEndDate>2016-05-30</adjustedEndDate>
            <calculationPeriodNumberOfDays>182</calculationPeriodNumberOfDays>
            <notionalAmount>100000000</notionalAmount>
            <fixedRate>0.05</fixedRate>
            <dayCountYearFraction>0.498630136986301</dayCountYearFraction>
          </calculationPeriod>
          <discountFactor>0.79938719343158</discountFactor>
          <forecastPaymentAmount>
            <currency>AUD</currency>
            <amount>2493150.68493150500000000</amount>
          </forecastPaymentAmount>
          <presentValueAmount>
            <currency>AUD</currency>
            <amount>1992992.7288294171518182039279</amount>
          </presentValueAmount>
        </paymentCalculationPeriod>
        <paymentCalculationPeriod>
          <adjustedPaymentDate>2016-11-29</adjustedPaymentDate>
          <calculationPeriod>
            <unadjustedStartDate>2016-05-29</unadjustedStartDate>
            <unadjustedEndDate>2016-11-29</unadjustedEndDate>
            <adjustedStartDate>2016-05-30</adjustedStartDate>
            <adjustedEndDate>2016-11-29</adjustedEndDate>
            <calculationPeriodNumberOfDays>183</calculationPeriodNumberOfDays>
            <notionalAmount>100000000</notionalAmount>
            <fixedRate>0.05</fixedRate>
            <dayCountYearFraction>0.501369863013699</dayCountYearFraction>
          </calculationPeriod>
          <discountFactor>0.771273367160946</discountFactor>
          <forecastPaymentAmount>
            <currency>AUD</currency>
            <amount>2506849.31506849500000000</amount>
          </forecastPaymentAmount>
          <presentValueAmount>
            <currency>AUD</currency>
            <amount>1933466.1121979893441356789963</amount>
          </presentValueAmount>
        </paymentCalculationPeriod>
        <paymentCalculationPeriod>
          <adjustedPaymentDate>2017-05-29</adjustedPaymentDate>
          <calculationPeriod>
            <unadjustedStartDate>2016-11-29</unadjustedStartDate>
            <unadjustedEndDate>2017-05-29</unadjustedEndDate>
            <adjustedStartDate>2016-11-29</adjustedStartDate>
            <adjustedEndDate>2017-05-29</adjustedEndDate>
            <calculationPeriodNumberOfDays>181</calculationPeriodNumberOfDays>
            <notionalAmount>100000000</notionalAmount>
            <fixedRate>0.05</fixedRate>
            <dayCountYearFraction>0.495890410958904</dayCountYearFraction>
          </calculationPeriod>
          <discountFactor>0.744734855135297</discountFactor>
          <forecastPaymentAmount>
            <currency>AUD</currency>
            <amount>2479452.05479452000000000</amount>
          </forecastPaymentAmount>
          <presentValueAmount>
            <currency>AUD</currency>
            <amount>1846534.3668423113316521341724</amount>
          </presentValueAmount>
        </paymentCalculationPeriod>
        <paymentCalculationPeriod>
          <adjustedPaymentDate>2017-11-29</adjustedPaymentDate>
          <calculationPeriod>
            <unadjustedStartDate>2017-05-29</unadjustedStartDate>
            <unadjustedEndDate>2017-11-29</unadjustedEndDate>
            <adjustedStartDate>2017-05-29</adjustedStartDate>
            <adjustedEndDate>2017-11-29</adjustedEndDate>
            <calculationPeriodNumberOfDays>184</calculationPeriodNumberOfDays>
            <notionalAmount>100000000</notionalAmount>
            <fixedRate>0.05</fixedRate>
            <dayCountYearFraction>0.504109589041096</dayCountYearFraction>
          </calculationPeriod>
          <discountFactor>0.717794314476932</discountFactor>
          <forecastPaymentAmount>
            <currency>AUD</currency>
            <amount>2520547.94520548000000000</amount>
          </forecastPaymentAmount>
          <presentValueAmount>
            <currency>AUD</currency>
            <amount>1809234.9844350070782434599874</amount>
          </presentValueAmount>
        </paymentCalculationPeriod>
        <paymentCalculationPeriod>
          <adjustedPaymentDate>2018-05-29</adjustedPaymentDate>
          <calculationPeriod>
            <unadjustedStartDate>2017-11-29</unadjustedStartDate>
            <unadjustedEndDate>2018-05-29</unadjustedEndDate>
            <adjustedStartDate>2017-11-29</adjustedStartDate>
            <adjustedEndDate>2018-05-29</adjustedEndDate>
            <calculationPeriodNumberOfDays>181</calculationPeriodNumberOfDays>
            <notionalAmount>100000000</notionalAmount>
            <fixedRate>0.05</fixedRate>
            <dayCountYearFraction>0.495890410958904</dayCountYearFraction>
          </calculationPeriod>
          <discountFactor>0.692286412863652</discountFactor>
          <forecastPaymentAmount>
            <currency>AUD</currency>
            <amount>2479452.05479452000000000</amount>
          </forecastPaymentAmount>
          <presentValueAmount>
            <currency>AUD</currency>
            <amount>1716490.9688811093740896367870</amount>
          </presentValueAmount>
        </paymentCalculationPeriod>
        <paymentCalculationPeriod>
          <adjustedPaymentDate>2018-11-29</adjustedPaymentDate>
          <calculationPeriod>
            <unadjustedStartDate>2018-05-29</unadjustedStartDate>
            <unadjustedEndDate>2018-11-29</unadjustedEndDate>
            <adjustedStartDate>2018-05-29</adjustedStartDate>
            <adjustedEndDate>2018-11-29</adjustedEndDate>
            <calculationPeriodNumberOfDays>184</calculationPeriodNumberOfDays>
            <notionalAmount>100000000</notionalAmount>
            <fixedRate>0.05</fixedRate>
            <dayCountYearFraction>0.504109589041096</dayCountYearFraction>
          </calculationPeriod>
          <discountFactor>0.67051625929033</discountFactor>
          <forecastPaymentAmount>
            <currency>AUD</currency>
            <amount>2520547.94520548000000000</amount>
          </forecastPaymentAmount>
          <presentValueAmount>
            <currency>AUD</currency>
            <amount>1690068.3795811061208308270084</amount>
          </presentValueAmount>
        </paymentCalculationPeriod>
        <paymentCalculationPeriod>
          <adjustedPaymentDate>2019-05-29</adjustedPaymentDate>
          <calculationPeriod>
            <unadjustedStartDate>2018-11-29</unadjustedStartDate>
            <unadjustedEndDate>2019-05-29</unadjustedEndDate>
            <adjustedStartDate>2018-11-29</adjustedStartDate>
            <adjustedEndDate>2019-05-29</adjustedEndDate>
            <calculationPeriodNumberOfDays>181</calculationPeriodNumberOfDays>
            <notionalAmount>100000000</notionalAmount>
            <fixedRate>0.05</fixedRate>
            <dayCountYearFraction>0.495890410958904</dayCountYearFraction>
          </calculationPeriod>
          <discountFactor>0.650351880369725</discountFactor>
          <forecastPaymentAmount>
            <currency>AUD</currency>
            <amount>2479452.05479452000000000</amount>
          </forecastPaymentAmount>
          <presentValueAmount>
            <currency>AUD</currency>
            <amount>1612516.3061221945066565039070</amount>
          </presentValueAmount>
        </paymentCalculationPeriod>
        <paymentCalculationPeriod>
          <adjustedPaymentDate>2019-11-29</adjustedPaymentDate>
          <calculationPeriod>
            <unadjustedStartDate>2019-05-29</unadjustedStartDate>
            <unadjustedEndDate>2019-11-29</unadjustedEndDate>
            <adjustedStartDate>2019-05-29</adjustedStartDate>
            <adjustedEndDate>2019-11-29</adjustedEndDate>
            <calculationPeriodNumberOfDays>184</calculationPeriodNumberOfDays>
            <notionalAmount>100000000</notionalAmount>
            <fixedRate>0.05</fixedRate>
            <dayCountYearFraction>0.504109589041096</dayCountYearFraction>
          </calculationPeriod>
          <discountFactor>0.631017190620842</discountFactor>
          <forecastPaymentAmount>
            <currency>AUD</currency>
            <amount>2520547.94520548000000000</amount>
          </forecastPaymentAmount>
          <presentValueAmount>
            <currency>AUD</currency>
            <amount>1590509.0832086979895984606142</amount>
          </presentValueAmount>
        </paymentCalculationPeriod>
        <paymentCalculationPeriod>
          <adjustedPaymentDate>2020-05-29</adjustedPaymentDate>
          <calculationPeriod>
            <unadjustedStartDate>2019-11-29</unadjustedStartDate>
            <unadjustedEndDate>2020-05-29</unadjustedEndDate>
            <adjustedStartDate>2019-11-29</adjustedStartDate>
            <adjustedEndDate>2020-05-29</adjustedEndDate>
            <calculationPeriodNumberOfDays>182</calculationPeriodNumberOfDays>
            <notionalAmount>100000000</notionalAmount>
            <fixedRate>0.05</fixedRate>
            <dayCountYearFraction>0.498630136986301</dayCountYearFraction>
          </calculationPeriod>
          <discountFactor>0.612984864492257</discountFactor>
          <forecastPaymentAmount>
            <currency>AUD</currency>
            <amount>2493150.68493150500000000</amount>
          </forecastPaymentAmount>
          <presentValueAmount>
            <currency>AUD</currency>
            <amount>1528263.6347615163184526478568</amount>
          </presentValueAmount>
        </paymentCalculationPeriod>
        <paymentCalculationPeriod>
          <adjustedPaymentDate>2020-11-30</adjustedPaymentDate>
          <calculationPeriod>
            <unadjustedStartDate>2020-05-29</unadjustedStartDate>
            <unadjustedEndDate>2020-11-29</unadjustedEndDate>
            <adjustedStartDate>2020-05-29</adjustedStartDate>
            <adjustedEndDate>2020-11-30</adjustedEndDate>
            <calculationPeriodNumberOfDays>185</calculationPeriodNumberOfDays>
            <notionalAmount>100000000</notionalAmount>
            <fixedRate>0.05</fixedRate>
            <dayCountYearFraction>0.506849315068493</dayCountYearFraction>
          </calculationPeriod>
          <discountFactor>0.593539967062968</discountFactor>
          <forecastPaymentAmount>
            <currency>AUD</currency>
            <amount>2534246.57534246500000000</amount>
          </forecastPaymentAmount>
          <presentValueAmount>
            <currency>AUD</currency>
            <amount>1504176.6288582061281548193361</amount>
          </presentValueAmount>
        </paymentCalculationPeriod>
        <paymentCalculationPeriod>
          <adjustedPaymentDate>2021-05-31</adjustedPaymentDate>
          <calculationPeriod>
            <unadjustedStartDate>2020-11-29</unadjustedStartDate>
            <unadjustedEndDate>2021-05-29</unadjustedEndDate>
            <adjustedStartDate>2020-11-30</adjustedStartDate>
            <adjustedEndDate>2021-05-31</adjustedEndDate>
            <calculationPeriodNumberOfDays>182</calculationPeriodNumberOfDays>
            <notionalAmount>100000000</notionalAmount>
            <fixedRate>0.05</fixedRate>
            <dayCountYearFraction>0.498630136986301</dayCountYearFraction>
          </calculationPeriod>
          <discountFactor>0.57524932325427</discountFactor>
          <forecastPaymentAmount>
            <currency>AUD</currency>
            <amount>2493150.68493150500000000</amount>
          </forecastPaymentAmount>
          <presentValueAmount>
            <currency>AUD</currency>
            <amount>1434183.2442777679772786487764</amount>
          </presentValueAmount>
        </paymentCalculationPeriod>
        <paymentCalculationPeriod>
          <adjustedPaymentDate>2021-11-29</adjustedPaymentDate>
          <calculationPeriod>
            <unadjustedStartDate>2021-05-29</unadjustedStartDate>
            <unadjustedEndDate>2021-11-29</unadjustedEndDate>
            <adjustedStartDate>2021-05-31</adjustedStartDate>
            <adjustedEndDate>2021-11-29</adjustedEndDate>
            <calculationPeriodNumberOfDays>182</calculationPeriodNumberOfDays>
            <notionalAmount>100000000</notionalAmount>
            <fixedRate>0.05</fixedRate>
            <dayCountYearFraction>0.498630136986301</dayCountYearFraction>
          </calculationPeriod>
          <discountFactor>0.557791715383562</discountFactor>
          <forecastPaymentAmount>
            <currency>AUD</currency>
            <amount>2493150.68493150500000000</amount>
          </forecastPaymentAmount>
          <presentValueAmount>
            <currency>AUD</currency>
            <amount>1390658.7972576466944947729208</amount>
          </presentValueAmount>
        </paymentCalculationPeriod>
        <paymentCalculationPeriod>
          <adjustedPaymentDate>2022-05-30</adjustedPaymentDate>
          <calculationPeriod>
            <unadjustedStartDate>2021-11-29</unadjustedStartDate>
            <unadjustedEndDate>2022-05-29</unadjustedEndDate>
            <adjustedStartDate>2021-11-29</adjustedStartDate>
            <adjustedEndDate>2022-05-30</adjustedEndDate>
            <calculationPeriodNumberOfDays>182</calculationPeriodNumberOfDays>
            <notionalAmount>100000000</notionalAmount>
            <fixedRate>0.05</fixedRate>
            <dayCountYearFraction>0.498630136986301</dayCountYearFraction>
          </calculationPeriod>
          <discountFactor>0.541084375837463</discountFactor>
          <forecastPaymentAmount>
            <currency>AUD</currency>
            <amount>2493150.68493150500000000</amount>
          </forecastPaymentAmount>
          <presentValueAmount>
            <currency>AUD</currency>
            <amount>1349004.8822249067527891679718</amount>
          </presentValueAmount>
        </paymentCalculationPeriod>
        <paymentCalculationPeriod>
          <adjustedPaymentDate>2022-11-29</adjustedPaymentDate>
          <calculationPeriod>
            <unadjustedStartDate>2022-05-29</unadjustedStartDate>
            <unadjustedEndDate>2022-11-29</unadjustedEndDate>
            <adjustedStartDate>2022-05-30</adjustedStartDate>
            <adjustedEndDate>2022-11-29</adjustedEndDate>
            <calculationPeriodNumberOfDays>183</calculationPeriodNumberOfDays>
            <notionalAmount>100000000</notionalAmount>
            <fixedRate>0.05</fixedRate>
            <dayCountYearFraction>0.501369863013699</dayCountYearFraction>
          </calculationPeriod>
          <discountFactor>0.524721335705089</discountFactor>
          <forecastPaymentAmount>
            <currency>AUD</currency>
            <amount>2506849.31506849500000000</amount>
          </forecastPaymentAmount>
          <presentValueAmount>
            <currency>AUD</currency>
            <amount>1315397.3210141281895531550711</amount>
          </presentValueAmount>
        </paymentCalculationPeriod>
        <paymentCalculationPeriod>
          <adjustedPaymentDate>2023-05-29</adjustedPaymentDate>
          <calculationPeriod>
            <unadjustedStartDate>2022-11-29</unadjustedStartDate>
            <unadjustedEndDate>2023-05-29</unadjustedEndDate>
            <adjustedStartDate>2022-11-29</adjustedStartDate>
            <adjustedEndDate>2023-05-29</adjustedEndDate>
            <calculationPeriodNumberOfDays>181</calculationPeriodNumberOfDays>
            <notionalAmount>100000000</notionalAmount>
            <fixedRate>0.05</fixedRate>
            <dayCountYearFraction>0.495890410958904</dayCountYearFraction>
          </calculationPeriod>
          <discountFactor>0.509205226195311</discountFactor>
          <forecastPaymentAmount>
            <currency>AUD</currency>
            <amount>2479452.05479452000000000</amount>
          </forecastPaymentAmount>
          <presentValueAmount>
            <currency>AUD</currency>
            <amount>1262549.9444020722004354924957</amount>
          </presentValueAmount>
        </paymentCalculationPeriod>
      </cashflows>
    </swapStream>
    <swapStream>
      <payerPartyReference href="Party2" />
      <receiverPartyReference href="Party1" />
      <calculationPeriodDates>
        <effectiveDate>
          <unadjustedDate id="unadjustedDate">2013-05-27</unadjustedDate>
          <dateAdjustments>
            <businessDayConvention>NONE</businessDayConvention>
          </dateAdjustments>
        </effectiveDate>
        <terminationDate>
          <unadjustedDate id="unadjustedDate">2023-05-29</unadjustedDate>
          <dateAdjustments>
            <businessDayConvention>MODFOLLOWING</businessDayConvention>
            <businessCenters>
              <businessCenter>Sydney</businessCenter>
            </businessCenters>
          </dateAdjustments>
        </terminationDate>
        <calculationPeriodDatesAdjustments>
          <businessCenters>
            <businessCenter>Sydney</businessCenter>
          </businessCenters>
        </calculationPeriodDatesAdjustments>
        <calculationPeriodFrequency>
          <periodMultiplier>6</periodMultiplier>
          <period>M</period>
        </calculationPeriodFrequency>
      </calculationPeriodDates>
      <paymentDates>
        <paymentFrequency>
          <periodMultiplier>6</periodMultiplier>
          <period>M</period>
        </paymentFrequency>
        <paymentDatesAdjustments>
          <businessCenters>
            <businessCenter>Sydney</businessCenter>
          </businessCenters>
        </paymentDatesAdjustments>
      </paymentDates>
      <resetDates>
        <fixingDates>
          <periodMultiplier>6</periodMultiplier>
          <dayType>Business</dayType>
          <businessCenters>
            <businessCenter>Sydney</businessCenter>
          </businessCenters>
          <dateRelativeTo href="resetDates" />
        </fixingDates>
        <resetFrequency>
          <periodMultiplier>6</periodMultiplier>
          <period>M</period>
        </resetFrequency>
        <resetDatesAdjustments>
          <businessCenters>
            <businessCenter>Sydney</businessCenter>
          </businessCenters>
        </resetDatesAdjustments>
      </resetDates>
      <calculationPeriodAmount>
        <calculation>
          <notionalSchedule>
            <notionalStepSchedule>
              <initialValue>100000000</initialValue>
              <currency>AUD</currency>
            </notionalStepSchedule>
          </notionalSchedule>
          <floatingRateCalculation>
            <floatingRateIndex>AUD-BBR-BBSW</floatingRateIndex>
            <indexTenor>
              <periodMultiplier>6</periodMultiplier>
              <period>M</period>
            </indexTenor>
            <spreadSchedule />
          </floatingRateCalculation>
          <dayCountFraction>ACT/365.FIXED</dayCountFraction>
        </calculation>
      </calculationPeriodAmount>
      <principalExchanges />
      <cashflows>
        <principalExchange>
          <adjustedPrincipalExchangeDate>2013-05-27</adjustedPrincipalExchangeDate>
          <principalExchangeAmount>-100000000</principalExchangeAmount>
          <discountFactor>0.999637939354568</discountFactor>
          <presentValuePrincipalExchangeAmount>
            <currency>CURRENCY NOT SPECIFIED</currency>
            <amount>-99963793.935456800000000</amount>
          </presentValuePrincipalExchangeAmount>
        </principalExchange>
        <principalExchange>
          <adjustedPrincipalExchangeDate>2023-05-29</adjustedPrincipalExchangeDate>
          <principalExchangeAmount>100000000</principalExchangeAmount>
          <discountFactor>0.509205226195311</discountFactor>
          <presentValuePrincipalExchangeAmount>
            <currency>CURRENCY NOT SPECIFIED</currency>
            <amount>50920522.619531100000000</amount>
          </presentValuePrincipalExchangeAmount>
        </principalExchange>
        <paymentCalculationPeriod>
          <adjustedPaymentDate>2013-11-29</adjustedPaymentDate>
          <calculationPeriod>
            <unadjustedStartDate>2013-05-27</unadjustedStartDate>
            <unadjustedEndDate>2013-11-29</unadjustedEndDate>
            <adjustedStartDate>2013-05-27</adjustedStartDate>
            <adjustedEndDate>2013-11-29</adjustedEndDate>
            <calculationPeriodNumberOfDays>186</calculationPeriodNumberOfDays>
            <notionalAmount>100000000</notionalAmount>
            <floatingRateDefinition>
              <calculatedRate>0.066754898549293</calculatedRate>
              <rateObservation>
                <adjustedFixingDate>2013-05-27</adjustedFixingDate>
                <forecastRate>0.066754898549293</forecastRate>
              </rateObservation>
              <spread>0</spread>
            </floatingRateDefinition>
            <dayCountYearFraction>0.50958904109589</dayCountYearFraction>
          </calculationPeriod>
          <discountFactor>0.966751410654946</discountFactor>
          <forecastPaymentAmount>
            <currency>AUD</currency>
            <amount>3401756.4740187638319904705770</amount>
          </forecastPaymentAmount>
          <presentValueAmount>
            <currency>AUD</currency>
            <amount>3288652.8699622350966664838336</amount>
          </presentValueAmount>
        </paymentCalculationPeriod>
        <paymentCalculationPeriod>
          <adjustedPaymentDate>2014-05-29</adjustedPaymentDate>
          <calculationPeriod>
            <unadjustedStartDate>2013-11-29</unadjustedStartDate>
            <unadjustedEndDate>2014-05-29</unadjustedEndDate>
            <adjustedStartDate>2013-11-29</adjustedStartDate>
            <adjustedEndDate>2014-05-29</adjustedEndDate>
            <calculationPeriodNumberOfDays>181</calculationPeriodNumberOfDays>
            <notionalAmount>100000000</notionalAmount>
            <floatingRateDefinition>
              <calculatedRate>0.0684956920762279</calculatedRate>
              <rateObservation>
                <adjustedFixingDate>2013-11-29</adjustedFixingDate>
                <forecastRate>0.0684956920762279</forecastRate>
              </rateObservation>
              <spread>0</spread>
            </floatingRateDefinition>
            <dayCountYearFraction>0.495890410958904</dayCountYearFraction>
          </calculationPeriod>
          <discountFactor>0.934993101284599</discountFactor>
          <forecastPaymentAmount>
            <currency>AUD</currency>
            <amount>3396635.6892595197699102238222</amount>
          </forecastPaymentAmount>
          <presentValueAmount>
            <currency>AUD</currency>
            <amount>3175830.9370347099039667367301</amount>
          </presentValueAmount>
        </paymentCalculationPeriod>
        <paymentCalculationPeriod>
          <adjustedPaymentDate>2014-11-28</adjustedPaymentDate>
          <calculationPeriod>
            <unadjustedStartDate>2014-05-29</unadjustedStartDate>
            <unadjustedEndDate>2014-11-29</unadjustedEndDate>
            <adjustedStartDate>2014-05-29</adjustedStartDate>
            <adjustedEndDate>2014-11-28</adjustedEndDate>
            <calculationPeriodNumberOfDays>183</calculationPeriodNumberOfDays>
            <notionalAmount>100000000</notionalAmount>
            <floatingRateDefinition>
              <calculatedRate>0.0657154320474463</calculatedRate>
              <rateObservation>
                <adjustedFixingDate>2014-05-29</adjustedFixingDate>
                <forecastRate>0.0657154320474463</forecastRate>
              </rateObservation>
              <spread>0</spread>
            </floatingRateDefinition>
            <dayCountYearFraction>0.501369863013699</dayCountYearFraction>
          </calculationPeriod>
          <discountFactor>0.905169804478298</discountFactor>
          <forecastPaymentAmount>
            <currency>AUD</currency>
            <amount>3294773.7163514196634474866864</amount>
          </forecastPaymentAmount>
          <presentValueAmount>
            <currency>AUD</currency>
            <amount>2982329.6806300498108679588104</amount>
          </presentValueAmount>
        </paymentCalculationPeriod>
        <paymentCalculationPeriod>
          <adjustedPaymentDate>2015-05-29</adjustedPaymentDate>
          <calculationPeriod>
            <unadjustedStartDate>2014-11-29</unadjustedStartDate>
            <unadjustedEndDate>2015-05-29</unadjustedEndDate>
            <adjustedStartDate>2014-11-28</adjustedStartDate>
            <adjustedEndDate>2015-05-29</adjustedEndDate>
            <calculationPeriodNumberOfDays>182</calculationPeriodNumberOfDays>
            <notionalAmount>100000000</notionalAmount>
            <floatingRateDefinition>
              <calculatedRate>0.0677031393463837</calculatedRate>
              <rateObservation>
                <adjustedFixingDate>2014-11-28</adjustedFixingDate>
                <forecastRate>0.0677031393463837</forecastRate>
              </rateObservation>
              <spread>0</spread>
            </floatingRateDefinition>
            <dayCountYearFraction>0.498630136986301</dayCountYearFraction>
          </calculationPeriod>
          <discountFactor>0.875610231343901</discountFactor>
          <forecastPaymentAmount>
            <currency>AUD</currency>
            <amount>3375882.5646689929479660789694</amount>
          </forecastPaymentAmount>
          <presentValueAmount>
            <currency>AUD</currency>
            <amount>2955957.3134396587435781807304</amount>
          </presentValueAmount>
        </paymentCalculationPeriod>
        <paymentCalculationPeriod>
          <adjustedPaymentDate>2015-11-30</adjustedPaymentDate>
          <calculationPeriod>
            <unadjustedStartDate>2015-05-29</unadjustedStartDate>
            <unadjustedEndDate>2015-11-29</unadjustedEndDate>
            <adjustedStartDate>2015-05-29</adjustedStartDate>
            <adjustedEndDate>2015-11-30</adjustedEndDate>
            <calculationPeriodNumberOfDays>185</calculationPeriodNumberOfDays>
            <notionalAmount>100000000</notionalAmount>
            <floatingRateDefinition>
              <calculatedRate>0.0882541536823072</calculatedRate>
              <rateObservation>
                <adjustedFixingDate>2015-05-29</adjustedFixingDate>
                <forecastRate>0.0882541536823072</forecastRate>
              </rateObservation>
              <spread>0</spread>
            </floatingRateDefinition>
            <dayCountYearFraction>0.506849315068493</dayCountYearFraction>
          </calculationPeriod>
          <discountFactor>0.838119826272326</discountFactor>
          <forecastPaymentAmount>
            <currency>AUD</currency>
            <amount>4473155.7345826923687730267050</amount>
          </forecastPaymentAmount>
          <presentValueAmount>
            <currency>AUD</currency>
            <amount>3749040.5071575049193035432575</amount>
          </presentValueAmount>
        </paymentCalculationPeriod>
        <paymentCalculationPeriod>
          <adjustedPaymentDate>2016-05-30</adjustedPaymentDate>
          <calculationPeriod>
            <unadjustedStartDate>2015-11-29</unadjustedStartDate>
            <unadjustedEndDate>2016-05-29</unadjustedEndDate>
            <adjustedStartDate>2015-11-30</adjustedStartDate>
            <adjustedEndDate>2016-05-30</adjustedEndDate>
            <calculationPeriodNumberOfDays>182</calculationPeriodNumberOfDays>
            <notionalAmount>100000000</notionalAmount>
            <floatingRateDefinition>
              <calculatedRate>0.0971720375103819</calculatedRate>
              <rateObservation>
                <adjustedFixingDate>2015-11-30</adjustedFixingDate>
                <forecastRate>0.0971720375103819</forecastRate>
              </rateObservation>
              <spread>0</spread>
            </floatingRateDefinition>
            <dayCountYearFraction>0.498630136986301</dayCountYearFraction>
          </calculationPeriod>
          <discountFactor>0.79938719343158</discountFactor>
          <forecastPaymentAmount>
            <currency>AUD</currency>
            <amount>4845290.6375039705977465578352</amount>
          </forecastPaymentAmount>
          <presentValueAmount>
            <currency>AUD</currency>
            <amount>3873263.2840746101158211166239</amount>
          </presentValueAmount>
        </paymentCalculationPeriod>
        <paymentCalculationPeriod>
          <adjustedPaymentDate>2016-11-29</adjustedPaymentDate>
          <calculationPeriod>
            <unadjustedStartDate>2016-05-29</unadjustedStartDate>
            <unadjustedEndDate>2016-11-29</unadjustedEndDate>
            <adjustedStartDate>2016-05-30</adjustedStartDate>
            <adjustedEndDate>2016-11-29</adjustedEndDate>
            <calculationPeriodNumberOfDays>183</calculationPeriodNumberOfDays>
            <notionalAmount>100000000</notionalAmount>
            <floatingRateDefinition>
              <calculatedRate>0.0727031782281268</calculatedRate>
              <rateObservation>
                <adjustedFixingDate>2016-05-30</adjustedFixingDate>
                <forecastRate>0.0727031782281268</forecastRate>
              </rateObservation>
              <spread>0</spread>
            </floatingRateDefinition>
            <dayCountYearFraction>0.501369863013699</dayCountYearFraction>
          </calculationPeriod>
          <discountFactor>0.771273367160946</discountFactor>
          <forecastPaymentAmount>
            <currency>AUD</currency>
            <amount>3645118.2508896477301175509033</amount>
          </forecastPaymentAmount>
          <presentValueAmount>
            <currency>AUD</currency>
            <amount>2811382.6270634765522593560346</amount>
          </presentValueAmount>
        </paymentCalculationPeriod>
        <paymentCalculationPeriod>
          <adjustedPaymentDate>2017-05-29</adjustedPaymentDate>
          <calculationPeriod>
            <unadjustedStartDate>2016-11-29</unadjustedStartDate>
            <unadjustedEndDate>2017-05-29</unadjustedEndDate>
            <adjustedStartDate>2016-11-29</adjustedStartDate>
            <adjustedEndDate>2017-05-29</adjustedEndDate>
            <calculationPeriodNumberOfDays>181</calculationPeriodNumberOfDays>
            <notionalAmount>100000000</notionalAmount>
            <floatingRateDefinition>
              <calculatedRate>0.0718603252184003</calculatedRate>
              <rateObservation>
                <adjustedFixingDate>2016-11-29</adjustedFixingDate>
                <forecastRate>0.0718603252184003</forecastRate>
              </rateObservation>
              <spread>0</spread>
            </floatingRateDefinition>
            <dayCountYearFraction>0.495890410958904</dayCountYearFraction>
          </calculationPeriod>
          <discountFactor>0.744734855135297</discountFactor>
          <forecastPaymentAmount>
            <currency>AUD</currency>
            <amount>3563484.6204193017604347921271</amount>
          </forecastPaymentAmount>
          <presentValueAmount>
            <currency>AUD</currency>
            <amount>2653851.2025648275144475199220</amount>
          </presentValueAmount>
        </paymentCalculationPeriod>
        <paymentCalculationPeriod>
          <adjustedPaymentDate>2017-11-29</adjustedPaymentDate>
          <calculationPeriod>
            <unadjustedStartDate>2017-05-29</unadjustedStartDate>
            <unadjustedEndDate>2017-11-29</unadjustedEndDate>
            <adjustedStartDate>2017-05-29</adjustedStartDate>
            <adjustedEndDate>2017-11-29</adjustedEndDate>
            <calculationPeriodNumberOfDays>184</calculationPeriodNumberOfDays>
            <notionalAmount>100000000</notionalAmount>
            <floatingRateDefinition>
              <calculatedRate>0.0744528513159893</calculatedRate>
              <rateObservation>
                <adjustedFixingDate>2017-05-29</adjustedFixingDate>
                <forecastRate>0.0744528513159893</forecastRate>
              </rateObservation>
              <spread>0</spread>
            </floatingRateDefinition>
            <dayCountYearFraction>0.504109589041096</dayCountYearFraction>
          </calculationPeriod>
          <discountFactor>0.717794314476932</discountFactor>
          <forecastPaymentAmount>
            <currency>AUD</currency>
            <amount>3753239.6279841189529079596273</amount>
          </forecastPaymentAmount>
          <presentValueAmount>
            <currency>AUD</currency>
            <amount>2694054.0658365159489506890063</amount>
          </presentValueAmount>
        </paymentCalculationPeriod>
        <paymentCalculationPeriod>
          <adjustedPaymentDate>2018-05-29</adjustedPaymentDate>
          <calculationPeriod>
            <unadjustedStartDate>2017-11-29</unadjustedStartDate>
            <unadjustedEndDate>2018-05-29</unadjustedEndDate>
            <adjustedStartDate>2017-11-29</adjustedStartDate>
            <adjustedEndDate>2018-05-29</adjustedEndDate>
            <calculationPeriodNumberOfDays>181</calculationPeriodNumberOfDays>
            <notionalAmount>100000000</notionalAmount>
            <floatingRateDefinition>
              <calculatedRate>0.0743024637930588</calculatedRate>
              <rateObservation>
                <adjustedFixingDate>2017-11-29</adjustedFixingDate>
                <forecastRate>0.0743024637930588</forecastRate>
              </rateObservation>
              <spread>0</spread>
            </floatingRateDefinition>
            <dayCountYearFraction>0.495890410958904</dayCountYearFraction>
          </calculationPeriod>
          <discountFactor>0.692286412863652</discountFactor>
          <forecastPaymentAmount>
            <currency>AUD</currency>
            <amount>3684587.9305599013227127255555</amount>
          </forecastPaymentAmount>
          <presentValueAmount>
            <currency>AUD</currency>
            <amount>2550790.1613280209731787667787</amount>
          </presentValueAmount>
        </paymentCalculationPeriod>
        <paymentCalculationPeriod>
          <adjustedPaymentDate>2018-11-29</adjustedPaymentDate>
          <calculationPeriod>
            <unadjustedStartDate>2018-05-29</unadjustedStartDate>
            <unadjustedEndDate>2018-11-29</unadjustedEndDate>
            <adjustedStartDate>2018-05-29</adjustedStartDate>
            <adjustedEndDate>2018-11-29</adjustedEndDate>
            <calculationPeriodNumberOfDays>184</calculationPeriodNumberOfDays>
            <notionalAmount>100000000</notionalAmount>
            <floatingRateDefinition>
              <calculatedRate>0.0644061324273699</calculatedRate>
              <rateObservation>
                <adjustedFixingDate>2018-05-29</adjustedFixingDate>
                <forecastRate>0.0644061324273699</forecastRate>
              </rateObservation>
              <spread>0</spread>
            </floatingRateDefinition>
            <dayCountYearFraction>0.504109589041096</dayCountYearFraction>
          </calculationPeriod>
          <discountFactor>0.67051625929033</discountFactor>
          <forecastPaymentAmount>
            <currency>AUD</currency>
            <amount>3246774.8949687847058206293410</amount>
          </forecastPaymentAmount>
          <presentValueAmount>
            <currency>AUD</currency>
            <amount>2177015.3573322235979795511744</amount>
          </presentValueAmount>
        </paymentCalculationPeriod>
        <paymentCalculationPeriod>
          <adjustedPaymentDate>2019-05-29</adjustedPaymentDate>
          <calculationPeriod>
            <unadjustedStartDate>2018-11-29</unadjustedStartDate>
            <unadjustedEndDate>2019-05-29</unadjustedEndDate>
            <adjustedStartDate>2018-11-29</adjustedStartDate>
            <adjustedEndDate>2019-05-29</adjustedEndDate>
            <calculationPeriodNumberOfDays>181</calculationPeriodNumberOfDays>
            <notionalAmount>100000000</notionalAmount>
            <floatingRateDefinition>
              <calculatedRate>0.0625245736866256</calculatedRate>
              <rateObservation>
                <adjustedFixingDate>2018-11-29</adjustedFixingDate>
                <forecastRate>0.0625245736866256</forecastRate>
              </rateObservation>
              <spread>0</spread>
            </floatingRateDefinition>
            <dayCountYearFraction>0.495890410958904</dayCountYearFraction>
          </calculationPeriod>
          <discountFactor>0.650351880369725</discountFactor>
          <forecastPaymentAmount>
            <currency>AUD</currency>
            <amount>3100533.6540491044106896034342</amount>
          </forecastPaymentAmount>
          <presentValueAmount>
            <currency>AUD</currency>
            <amount>2016437.8920604494710515808181</amount>
          </presentValueAmount>
        </paymentCalculationPeriod>
        <paymentCalculationPeriod>
          <adjustedPaymentDate>2019-11-29</adjustedPaymentDate>
          <calculationPeriod>
            <unadjustedStartDate>2019-05-29</unadjustedStartDate>
            <unadjustedEndDate>2019-11-29</unadjustedEndDate>
            <adjustedStartDate>2019-05-29</adjustedStartDate>
            <adjustedEndDate>2019-11-29</adjustedEndDate>
            <calculationPeriodNumberOfDays>184</calculationPeriodNumberOfDays>
            <notionalAmount>100000000</notionalAmount>
            <floatingRateDefinition>
              <calculatedRate>0.0607814502696129</calculatedRate>
              <rateObservation>
                <adjustedFixingDate>2019-05-29</adjustedFixingDate>
                <forecastRate>0.0607814502696129</forecastRate>
              </rateObservation>
              <spread>0</spread>
            </floatingRateDefinition>
            <dayCountYearFraction>0.504109589041096</dayCountYearFraction>
          </calculationPeriod>
          <discountFactor>0.631017190620842</discountFactor>
          <forecastPaymentAmount>
            <currency>AUD</currency>
            <amount>3064051.1916736372688378111738</amount>
          </forecastPaymentAmount>
          <presentValueAmount>
            <currency>AUD</currency>
            <amount>1933468.9748883416564023544819</amount>
          </presentValueAmount>
        </paymentCalculationPeriod>
        <paymentCalculationPeriod>
          <adjustedPaymentDate>2020-05-29</adjustedPaymentDate>
          <calculationPeriod>
            <unadjustedStartDate>2019-11-29</unadjustedStartDate>
            <unadjustedEndDate>2020-05-29</unadjustedEndDate>
            <adjustedStartDate>2019-11-29</adjustedStartDate>
            <adjustedEndDate>2020-05-29</adjustedEndDate>
            <calculationPeriodNumberOfDays>182</calculationPeriodNumberOfDays>
            <notionalAmount>100000000</notionalAmount>
            <floatingRateDefinition>
              <calculatedRate>0.0589961238310783</calculatedRate>
              <rateObservation>
                <adjustedFixingDate>2019-11-29</adjustedFixingDate>
                <forecastRate>0.0589961238310783</forecastRate>
              </rateObservation>
              <spread>0</spread>
            </floatingRateDefinition>
            <dayCountYearFraction>0.498630136986301</dayCountYearFraction>
          </calculationPeriod>
          <discountFactor>0.612984864492257</discountFactor>
          <forecastPaymentAmount>
            <currency>AUD</currency>
            <amount>2941724.5307551349686365158368</amount>
          </forecastPaymentAmount>
          <presentValueAmount>
            <currency>AUD</currency>
            <amount>1803232.6128584847183872293999</amount>
          </presentValueAmount>
        </paymentCalculationPeriod>
        <paymentCalculationPeriod>
          <adjustedPaymentDate>2020-11-30</adjustedPaymentDate>
          <calculationPeriod>
            <unadjustedStartDate>2020-05-29</unadjustedStartDate>
            <unadjustedEndDate>2020-11-29</unadjustedEndDate>
            <adjustedStartDate>2020-05-29</adjustedStartDate>
            <adjustedEndDate>2020-11-30</adjustedEndDate>
            <calculationPeriodNumberOfDays>185</calculationPeriodNumberOfDays>
            <notionalAmount>100000000</notionalAmount>
            <floatingRateDefinition>
              <calculatedRate>0.0646363500676411</calculatedRate>
              <rateObservation>
                <adjustedFixingDate>2020-05-29</adjustedFixingDate>
                <forecastRate>0.0646363500676411</forecastRate>
              </rateObservation>
              <spread>0</spread>
            </floatingRateDefinition>
            <dayCountYearFraction>0.506849315068493</dayCountYearFraction>
          </calculationPeriod>
          <discountFactor>0.593539967062968</discountFactor>
          <forecastPaymentAmount>
            <currency>AUD</currency>
            <amount>3276088.9760311232726029441862</amount>
          </forecastPaymentAmount>
          <presentValueAmount>
            <currency>AUD</currency>
            <amount>1944489.7429288654688364112666</amount>
          </presentValueAmount>
        </paymentCalculationPeriod>
        <paymentCalculationPeriod>
          <adjustedPaymentDate>2021-05-31</adjustedPaymentDate>
          <calculationPeriod>
            <unadjustedStartDate>2020-11-29</unadjustedStartDate>
            <unadjustedEndDate>2021-05-29</unadjustedEndDate>
            <adjustedStartDate>2020-11-30</adjustedStartDate>
            <adjustedEndDate>2021-05-31</adjustedEndDate>
            <calculationPeriodNumberOfDays>182</calculationPeriodNumberOfDays>
            <notionalAmount>100000000</notionalAmount>
            <floatingRateDefinition>
              <calculatedRate>0.0637667602158778</calculatedRate>
              <rateObservation>
                <adjustedFixingDate>2020-11-30</adjustedFixingDate>
                <forecastRate>0.0637667602158778</forecastRate>
              </rateObservation>
              <spread>0</spread>
            </floatingRateDefinition>
            <dayCountYearFraction>0.498630136986301</dayCountYearFraction>
          </calculationPeriod>
          <discountFactor>0.57524932325427</discountFactor>
          <forecastPaymentAmount>
            <currency>AUD</currency>
            <amount>3179602.8381615756141061290018</amount>
          </forecastPaymentAmount>
          <presentValueAmount>
            <currency>AUD</currency>
            <amount>1829064.3808698025502872037898</amount>
          </presentValueAmount>
        </paymentCalculationPeriod>
        <paymentCalculationPeriod>
          <adjustedPaymentDate>2021-11-29</adjustedPaymentDate>
          <calculationPeriod>
            <unadjustedStartDate>2021-05-29</unadjustedStartDate>
            <unadjustedEndDate>2021-11-29</unadjustedEndDate>
            <adjustedStartDate>2021-05-31</adjustedStartDate>
            <adjustedEndDate>2021-11-29</adjustedEndDate>
            <calculationPeriodNumberOfDays>182</calculationPeriodNumberOfDays>
            <notionalAmount>100000000</notionalAmount>
            <floatingRateDefinition>
              <calculatedRate>0.0627674016988723</calculatedRate>
              <rateObservation>
                <adjustedFixingDate>2021-05-31</adjustedFixingDate>
                <forecastRate>0.0627674016988723</forecastRate>
              </rateObservation>
              <spread>0</spread>
            </floatingRateDefinition>
            <dayCountYearFraction>0.498630136986301</dayCountYearFraction>
          </calculationPeriod>
          <discountFactor>0.557791715383562</discountFactor>
          <forecastPaymentAmount>
            <currency>AUD</currency>
            <amount>3129771.8107382877058632248362</amount>
          </forecastPaymentAmount>
          <presentValueAmount>
            <currency>AUD</currency>
            <amount>1745760.7870708264508872628459</amount>
          </presentValueAmount>
        </paymentCalculationPeriod>
        <paymentCalculationPeriod>
          <adjustedPaymentDate>2022-05-30</adjustedPaymentDate>
          <calculationPeriod>
            <unadjustedStartDate>2021-11-29</unadjustedStartDate>
            <unadjustedEndDate>2022-05-29</unadjustedEndDate>
            <adjustedStartDate>2021-11-29</adjustedStartDate>
            <adjustedEndDate>2022-05-30</adjustedEndDate>
            <calculationPeriodNumberOfDays>182</calculationPeriodNumberOfDays>
            <notionalAmount>100000000</notionalAmount>
            <floatingRateDefinition>
              <calculatedRate>0.0619246815420841</calculatedRate>
              <rateObservation>
                <adjustedFixingDate>2021-11-29</adjustedFixingDate>
                <forecastRate>0.0619246815420841</forecastRate>
              </rateObservation>
              <spread>0</spread>
            </floatingRateDefinition>
            <dayCountYearFraction>0.498630136986301</dayCountYearFraction>
          </calculationPeriod>
          <discountFactor>0.541084375837463</discountFactor>
          <forecastPaymentAmount>
            <currency>AUD</currency>
            <amount>3087751.2440162459836076689914</amount>
          </forecastPaymentAmount>
          <presentValueAmount>
            <currency>AUD</currency>
            <amount>1670733.9546098803679541932316</amount>
          </presentValueAmount>
        </paymentCalculationPeriod>
        <paymentCalculationPeriod>
          <adjustedPaymentDate>2022-11-29</adjustedPaymentDate>
          <calculationPeriod>
            <unadjustedStartDate>2022-05-29</unadjustedStartDate>
            <unadjustedEndDate>2022-11-29</unadjustedEndDate>
            <adjustedStartDate>2022-05-30</adjustedStartDate>
            <adjustedEndDate>2022-11-29</adjustedEndDate>
            <calculationPeriodNumberOfDays>183</calculationPeriodNumberOfDays>
            <notionalAmount>100000000</notionalAmount>
            <floatingRateDefinition>
              <calculatedRate>0.0621980897747258</calculatedRate>
              <rateObservation>
                <adjustedFixingDate>2022-05-30</adjustedFixingDate>
                <forecastRate>0.0621980897747258</forecastRate>
              </rateObservation>
              <spread>0</spread>
            </floatingRateDefinition>
            <dayCountYearFraction>0.501369863013699</dayCountYearFraction>
          </calculationPeriod>
          <discountFactor>0.524721335705089</discountFactor>
          <forecastPaymentAmount>
            <currency>AUD</currency>
            <amount>3118424.7750068026840389368734</amount>
          </forecastPaymentAmount>
          <presentValueAmount>
            <currency>AUD</currency>
            <amount>1636304.0132374111446352656459</amount>
          </presentValueAmount>
        </paymentCalculationPeriod>
        <paymentCalculationPeriod>
          <adjustedPaymentDate>2023-05-29</adjustedPaymentDate>
          <calculationPeriod>
            <unadjustedStartDate>2022-11-29</unadjustedStartDate>
            <unadjustedEndDate>2023-05-29</unadjustedEndDate>
            <adjustedStartDate>2022-11-29</adjustedStartDate>
            <adjustedEndDate>2023-05-29</adjustedEndDate>
            <calculationPeriodNumberOfDays>181</calculationPeriodNumberOfDays>
            <notionalAmount>100000000</notionalAmount>
            <floatingRateDefinition>
              <calculatedRate>0.0614475077939436</calculatedRate>
              <rateObservation>
                <adjustedFixingDate>2022-11-29</adjustedFixingDate>
                <forecastRate>0.0614475077939436</forecastRate>
              </rateObservation>
              <spread>0</spread>
            </floatingRateDefinition>
            <dayCountYearFraction>0.495890410958904</dayCountYearFraction>
          </calculationPeriod>
          <discountFactor>0.509205226195311</discountFactor>
          <forecastPaymentAmount>
            <currency>AUD</currency>
            <amount>3047122.9892339148334519693814</amount>
          </forecastPaymentAmount>
          <presentValueAmount>
            <currency>AUD</currency>
            <amount>1551610.9509777878077829275690</amount>
          </presentValueAmount>
        </paymentCalculationPeriod>
      </cashflows>
    </swapStream>
  </swap>
</Trade>